{
  "hero_slides": [
    {
      "title": "Welcome to Gallery The Illusions",
      "subtitle": "Where Art Meets Imagination",
      "description": "Discover extraordinary artworks from talented artists around the world in our curated collection.",
      "image_url": "blob:http://localhost:5173/6778ff27-832b-43d6-b962-11f46e8f5040",
      "image_file": {},
      "cta_text": "Explore Gallery",
      "cta_link": "/gallery",
      "text_position": "center",
      "text_color": "#ffffff",
      "active": true,
      "updated_at": "2025-06-14T23:43:46.141Z",
      "id": "1"
    },
    {
      "title": "Featured Artists Showcase",
      "subtitle": "Meet Our Creative Community",
      "description": "Get to know the passionate artists who bring their unique visions to life through stunning visual art.",
      "image_url": "blob:http://localhost:5173/d64cb985-4d84-4e9d-b692-e9085f1610b8",
      "image_file": {},
      "cta_text": "Meet Artists",
      "cta_link": "/artists",
      "text_position": "center",
      "text_color": "#ffffff",
      "active": true,
      "updated_at": "2025-06-14T23:29:23.186Z",
      "id": "2"
    },
    {
      "title": "Exclusive Art Auctions",
      "subtitle": "Bid on Rare Masterpieces",
      "description": "Participate in our exciting art auctions and own a piece of contemporary artistic excellence.",
      "image_url": "blob:http://localhost:5173/5ecf3514-79ff-41a7-8382-c6d17a10c881",
      "image_file": {},
      "cta_text": "View Auctions",
      "cta_link": "/auctions",
      "text_position": "center",
      "text_color": "#ffffff",
      "active": true,
      "updated_at": "2025-06-14T23:29:47.024Z",
      "id": "3"
    },
    {
      "title": "test edit",
      "subtitle": "test edit",
      "description": "test edit",
      "image_url": "blob:http://localhost:5173/c83991c0-b0f4-4986-9aef-99915c1d6ac9",
      "image_file": {},
      "cta_text": "Explore Gallery",
      "cta_link": "/gallery",
      "text_position": "center",
      "text_color": "#ffffff",
      "active": true,
      "updated_at": "2025-06-14T23:25:04.277Z",
      "id": "4"
    }
  ]
}